SolMuseum/__init__.py
SolMuseum/_version.py
SolMuseum/module_generator.py
SolMuseum/ae/__init__.py
SolMuseum/num_api/__init__.py
SolMuseum/num_api/pde/__init__.py
SolMuseum/num_api/pde/minmod_limiter.py
SolMuseum/num_api/pde/num_api_kt1.py
SolMuseum/num_api/pde/num_api_weno3.py
SolMuseum/num_api/pde/test/__init__.py
SolMuseum/num_api/pde/test/test_minmod.py
SolMuseum/ode/__init__.py
SolMuseum/pde/__init__.py
SolMuseum/pde/basic.py
SolMuseum/pde/gas/__init__.py
SolMuseum/pde/gas/ngs_pipe.py
SolMuseum/pde/gas/util.py
SolMuseum/pde/gas/broken_pipe/__init__.py
SolMuseum/pde/gas/broken_pipe/broken_ngs_pipe.py
SolMuseum/pde/gas/broken_pipe/cdm_broken.py
SolMuseum/pde/gas/broken_pipe/cha_broken.py
SolMuseum/pde/gas/broken_pipe/euler_broken.py
SolMuseum/pde/gas/broken_pipe/firstorder_broken.py
SolMuseum/pde/gas/broken_pipe/kt1_broken.py
SolMuseum/pde/gas/broken_pipe/kt2_broken.py
SolMuseum/pde/gas/broken_pipe/weno3_broken.py
SolMuseum/pde/gas/broken_pipe/test_leak/__init__.py
SolMuseum/pde/gas/broken_pipe/test_leak/test_cdm.py
SolMuseum/pde/gas/broken_pipe/test_leak/test_cha.py
SolMuseum/pde/gas/broken_pipe/test_leak/test_euler.py
SolMuseum/pde/gas/broken_pipe/test_leak/test_kt1.py
SolMuseum/pde/gas/broken_pipe/test_leak/test_kt2.py
SolMuseum/pde/gas/broken_pipe/test_leak/test_weno3.py
SolMuseum/pde/gas/broken_pipe/test_leak/data/res.xlsx
SolMuseum/pde/gas/broken_pipe/test_leak/data/sol0.pkl
SolMuseum/pde/gas/broken_pipe/test_rup/__init__.py
SolMuseum/pde/gas/broken_pipe/test_rup/test_cdm.py
SolMuseum/pde/gas/broken_pipe/test_rup/test_cha.py
SolMuseum/pde/gas/broken_pipe/test_rup/test_euler.py
SolMuseum/pde/gas/broken_pipe/test_rup/test_kt1.py
SolMuseum/pde/gas/broken_pipe/test_rup/test_kt2.py
SolMuseum/pde/gas/broken_pipe/test_rup/test_weno3.py
SolMuseum/pde/gas/broken_pipe/test_rup/data/res.xlsx
SolMuseum/pde/gas/test/__init__.py
SolMuseum/pde/gas/test/test_cdm.py
SolMuseum/pde/gas/test/test_cha.py
SolMuseum/pde/gas/test/test_euler.py
SolMuseum/pde/gas/test/test_kt1.py
SolMuseum-0.1.3.dist-info/LICENSE
SolMuseum-0.1.3.dist-info/METADATA
SolMuseum-0.1.3.dist-info/WHEEL
SolMuseum-0.1.3.dist-info/top_level.txt
SolMuseum-0.1.3.dist-info/RECORD
