Metadata-Version: 2.1
Name: SolMuseum
Version: 0.1.3
Summary: The modelling library for the simulation modelling language Solverz
Author-email: Ruizhi Yu <rz.yu@foxmail.com>
Project-URL: Homepage, https://github.com/smallbunnies/SolMuseum
Project-URL: Issues, https://github.com/smallbunnies/SolMuseum/issues
Classifier: Programming Language :: Python :: 3.10
Classifier: Programming Language :: Python :: 3.11
Classifier: Programming Language :: Python :: 3.12
Classifier: License :: OSI Approved :: MIT License
Classifier: Operating System :: OS Independent
Requires-Python: >=3.10
License-File: LICENSE
Requires-Dist: Solverz
